README.rst
setup.cfg
setup.py
kik_unofficial/__init__.py
kik_unofficial/cmdline.py
kik_unofficial/cryptographic_utils.py
kik_unofficial/kik_exceptions.py
kik_unofficial/kikclient.py
kik_unofficial/utilities.py
kik_unofficial.egg-info/PKG-INFO
kik_unofficial.egg-info/SOURCES.txt
kik_unofficial.egg-info/dependency_links.txt
kik_unofficial.egg-info/entry_points.txt
kik_unofficial.egg-info/requires.txt
kik_unofficial.egg-info/top_level.txt