Metadata-Version: 1.1
Name: kik-unofficial
Version: 0.2.1
Summary: Python API for writing unoffical kik bots that act like humans
Home-page: https://github.com/tomer8007/kik-bot-api-unofficial
Author: Tomer
Author-email: tomer8007@gmail.com
License: MIT
Download-URL: https://github.com/tomer8007/kik-bot-api-unofficial/tarball/master
Keywords: kik,bot,kikbot,kik-messenger-platform,api,unofficial,python
Platform: UNKNOWN
Classifier: Development Status :: 3 - Alpha
Classifier: Intended Audience :: Developers
Classifier: Programming Language :: Python :: 3
